{
  "Bench press - dumbbell decline": [
    {
      "repetitions": 5,
      "weight": {
        "unit": "kg",
        "amount": 30
      },
      "time": "2024.03.23 14-17-35",
      "type": "maxWeight",
      "gymLocation": "clever fit Garching",
      "comment": ""
    }
  ],
  "Chest press - weight plates decline": [
    {
      "repetitions": 5,
      "weight": {
        "unit": "kg",
        "amount": 30
      },
      "time": "2024.03.23 14-18-07",
      "type": "maxWeight",
      "gymLocation": "clever fit Garching",
      "comment": ""
    }
  ],
  "Butterfly": [
    {
      "repetitions": 6,
      "weight": {
        "unit": "kg",
        "amount": 57
      },
      "time": "2024.03.23 14-23-56",
      "type": "maxWeight",
      "gymLocation": "clever fit Garching",
      "comment": ""
    }
  ]
}